casual/__init__.py
casual/celery_worker.py
casual/cli.py
casual/config.py
casual/database.py
casual/hooks.py
casual/signals.py
casual/static/favi.png
casual/static/favicon.ico
casual/translations/de/LC_MESSAGES/casual.po
casual/translations/ro/LC_MESSAGES/casual.po
casual/util/__init__.py
casual/util/email.py
casual/util/lists.py
casual/util/text.py
casual/util/url.py
casual/wsgi.py
casual_admin/__init__.py
casual_admin/bp.py
casual_admin/resources.py
casual_admin/routes.py
casual_admin/templates/admin.base.html.j2
casual_auth/__init__.py
casual_auth/admin/__init__.py
casual_auth/admin/permission.py
casual_auth/admin/role.py
casual_auth/admin/user.py
casual_auth/api/__init__.py
casual_auth/api/permission.py
casual_auth/api/role.py
casual_auth/api/user.py
casual_auth/blueprints.py
casual_auth/cli.py
casual_auth/decorators.py
casual_auth/emails.py
casual_auth/forms.py
casual_auth/hooks/__init__.py
casual_auth/hooks/roles.py
casual_auth/hooks/users.py
casual_auth/models.py
casual_auth/password.py
casual_auth/routes/__init__.py
casual_auth/routes/confirmation.py
casual_auth/routes/registration.py
casual_auth/schemas/__init__.py
casual_auth/schemas/permission.py
casual_auth/schemas/role.py
casual_auth/schemas/user.py
casual_auth/signals.py
casual_auth/templates/auth/admin.base.html.j2
casual_auth/templates/auth/admin.permission.list.html.j2
casual_auth/templates/auth/admin.role.edit.html.j2
casual_auth/templates/auth/admin.role.list.html.j2
casual_auth/templates/auth/admin.role.menu.html.j2
casual_auth/templates/auth/admin.role.read.html.j2
casual_auth/templates/auth/admin.role.users.html.j2
casual_auth/templates/auth/admin.user.base.html.j2
casual_auth/templates/auth/admin.user.edit.html.j2
casual_auth/templates/auth/admin.user.list.html.j2
casual_auth/templates/auth/admin.user.list_old.html.j2
casual_auth/templates/auth/admin.user.menu.html.j2
casual_auth/templates/auth/admin.user.read.html.j2
casual_auth/templates/auth/admin.user.roles.html.j2
casual-2024.1.3.dist-info/LICENSE
casual-2024.1.3.dist-info/METADATA
casual-2024.1.3.dist-info/WHEEL
casual-2024.1.3.dist-info/entry_points.txt
casual-2024.1.3.dist-info/RECORD
